json_advanced/__init__.py
json_advanced/json_encoder.py
json_advanced/package_data.dat
json_advanced-0.12.7.dist-info/LICENSE.txt
json_advanced-0.12.7.dist-info/METADATA
json_advanced-0.12.7.dist-info/WHEEL
json_advanced-0.12.7.dist-info/top_level.txt
json_advanced-0.12.7.dist-info/RECORD
