Metadata-Version: 2.2
Name: json-advanced
Version: 0.12.7
Summary: This Python package provides an extended JSON encoder class, `JSONSerializer`, that enables encoding of complex Python data types such as `datetime.datetime`, `datetime.date`, `datetime.time`, `bytes` and `uuid`. It also supports objects that have a `to_json` method, allowing for customizable JSON encoding.
Author-email: Mahdi Kiani <mahdikiany@gmail.com>
Maintainer-email: Mahdi Kiani <mahdikiany@gmail.com>
License: Copyright (c) 2024 Mahdi Kiani
Project-URL: Homepage, https://github.com/mahdikiani/json-advanced
Project-URL: Bug Reports, https://github.com/mahdikiani/json-advanced/issues
Project-URL: Say Thanks!, https://saythanks.io/to/mahdikiani
Project-URL: Source, https://github.com/mahdikiani/json-advanced
Keywords: json,serialization,datetime,bytes,uuid,path
Classifier: Development Status :: 5 - Production/Stable
Classifier: Intended Audience :: Developers
Classifier: Topic :: Software Development :: Build Tools
Classifier: License :: OSI Approved :: MIT License
Classifier: Programming Language :: Python :: 3
Classifier: Programming Language :: Python :: 3.8
Classifier: Programming Language :: Python :: 3.9
Classifier: Programming Language :: Python :: 3.10
Classifier: Programming Language :: Python :: 3.11
Classifier: Programming Language :: Python :: 3.12
Classifier: Programming Language :: Python :: 3 :: Only
Requires-Python: >=3.10
License-File: LICENSE.txt
Provides-Extra: dev
Requires-Dist: check-manifest; extra == "dev"
Provides-Extra: test
Requires-Dist: coverage; extra == "test"
